{
  "activeChannel": {
    "channelId": "0xcb7b7c23c32c77123256cb6540cbd156c496d6865ce071768b66470225ea48af",
    "buyer": "0xf39Fd6e51aad88F6F4ce6aB8827279cffFb92266",
    "seller": "0x3C44CdDdB6a900fa2b585dd299e03d12FA4293BC",
    "balance": "9.990000",
    "nonce": 100,
    "isOpen": true
  },
  "channelContractAddress": "0x922D6956C99E12DFeB3224DEA977D0939758A1Fe",
  "logs": [
    {
      "timestamp": "2026-06-05T03:05:44.208Z",
      "type": "MICRO-PAYMENT",
      "channelId": "0xcb7b7c23c32c77123256cb6540cbd156c496d6865ce071768b66470225ea48af",
      "amount": "0.000100",
      "recipient": "0x3C44CdDdB6a900fa2b585dd299e03d12FA4293BC",
      "status": "SUCCESS",
      "description": "Micropayment of $0.000100 USDC for Benchmark run 99 validated"
    },
    {
      "timestamp": "2026-06-05T03:05:44.179Z",
      "type": "MICRO-PAYMENT",
      "channelId": "0xcb7b7c23c32c77123256cb6540cbd156c496d6865ce071768b66470225ea48af",
      "amount": "0.000100",
      "recipient": "0x3C44CdDdB6a900fa2b585dd299e03d12FA4293BC",
      "status": "SUCCESS",
      "description": "Micropayment of $0.000100 USDC for Benchmark run 98 validated"
    },
    {
      "timestamp": "2026-06-05T03:05:44.152Z",
      "type": "MICRO-PAYMENT",
      "channelId": "0xcb7b7c23c32c77123256cb6540cbd156c496d6865ce071768b66470225ea48af",
      "amount": "0.000100",
      "recipient": "0x3C44CdDdB6a900fa2b585dd299e03d12FA4293BC",
      "status": "SUCCESS",
      "description": "Micropayment of $0.000100 USDC for Benchmark run 97 validated"
    },
    {
      "timestamp": "2026-06-05T03:05:44.123Z",
      "type": "MICRO-PAYMENT",
      "channelId": "0xcb7b7c23c32c77123256cb6540cbd156c496d6865ce071768b66470225ea48af",
      "amount": "0.000100",
      "recipient": "0x3C44CdDdB6a900fa2b585dd299e03d12FA4293BC",
      "status": "SUCCESS",
      "description": "Micropayment of $0.000100 USDC for Benchmark run 96 validated"
    },
    {
      "timestamp": "2026-06-05T03:05:44.094Z",
      "type": "MICRO-PAYMENT",
      "channelId": "0xcb7b7c23c32c77123256cb6540cbd156c496d6865ce071768b66470225ea48af",
      "amount": "0.000100",
      "recipient": "0x3C44CdDdB6a900fa2b585dd299e03d12FA4293BC",
      "status": "SUCCESS",
      "description": "Micropayment of $0.000100 USDC for Benchmark run 95 validated"
    },
    {
      "timestamp": "2026-06-05T03:05:44.061Z",
      "type": "MICRO-PAYMENT",
      "channelId": "0xcb7b7c23c32c77123256cb6540cbd156c496d6865ce071768b66470225ea48af",
      "amount": "0.000100",
      "recipient": "0x3C44CdDdB6a900fa2b585dd299e03d12FA4293BC",
      "status": "SUCCESS",
      "description": "Micropayment of $0.000100 USDC for Benchmark run 94 validated"
    },
    {
      "timestamp": "2026-06-05T03:05:44.029Z",
      "type": "MICRO-PAYMENT",
      "channelId": "0xcb7b7c23c32c77123256cb6540cbd156c496d6865ce071768b66470225ea48af",
      "amount": "0.000100",
      "recipient": "0x3C44CdDdB6a900fa2b585dd299e03d12FA4293BC",
      "status": "SUCCESS",
      "description": "Micropayment of $0.000100 USDC for Benchmark run 93 validated"
    },
    {
      "timestamp": "2026-06-05T03:05:44.003Z",
      "type": "MICRO-PAYMENT",
      "channelId": "0xcb7b7c23c32c77123256cb6540cbd156c496d6865ce071768b66470225ea48af",
      "amount": "0.000100",
      "recipient": "0x3C44CdDdB6a900fa2b585dd299e03d12FA4293BC",
      "status": "SUCCESS",
      "description": "Micropayment of $0.000100 USDC for Benchmark run 92 validated"
    },
    {
      "timestamp": "2026-06-05T03:05:43.977Z",
      "type": "MICRO-PAYMENT",
      "channelId": "0xcb7b7c23c32c77123256cb6540cbd156c496d6865ce071768b66470225ea48af",
      "amount": "0.000100",
      "recipient": "0x3C44CdDdB6a900fa2b585dd299e03d12FA4293BC",
      "status": "SUCCESS",
      "description": "Micropayment of $0.000100 USDC for Benchmark run 91 validated"
    },
    {
      "timestamp": "2026-06-05T03:05:43.940Z",
      "type": "MICRO-PAYMENT",
      "channelId": "0xcb7b7c23c32c77123256cb6540cbd156c496d6865ce071768b66470225ea48af",
      "amount": "0.000100",
      "recipient": "0x3C44CdDdB6a900fa2b585dd299e03d12FA4293BC",
      "status": "SUCCESS",
      "description": "Micropayment of $0.000100 USDC for Benchmark run 90 validated"
    },
    {
      "timestamp": "2026-06-05T03:05:43.903Z",
      "type": "MICRO-PAYMENT",
      "channelId": "0xcb7b7c23c32c77123256cb6540cbd156c496d6865ce071768b66470225ea48af",
      "amount": "0.000100",
      "recipient": "0x3C44CdDdB6a900fa2b585dd299e03d12FA4293BC",
      "status": "SUCCESS",
      "description": "Micropayment of $0.000100 USDC for Benchmark run 89 validated"
    },
    {
      "timestamp": "2026-06-05T03:05:43.873Z",
      "type": "MICRO-PAYMENT",
      "channelId": "0xcb7b7c23c32c77123256cb6540cbd156c496d6865ce071768b66470225ea48af",
      "amount": "0.000100",
      "recipient": "0x3C44CdDdB6a900fa2b585dd299e03d12FA4293BC",
      "status": "SUCCESS",
      "description": "Micropayment of $0.000100 USDC for Benchmark run 88 validated"
    },
    {
      "timestamp": "2026-06-05T03:05:43.843Z",
      "type": "MICRO-PAYMENT",
      "channelId": "0xcb7b7c23c32c77123256cb6540cbd156c496d6865ce071768b66470225ea48af",
      "amount": "0.000100",
      "recipient": "0x3C44CdDdB6a900fa2b585dd299e03d12FA4293BC",
      "status": "SUCCESS",
      "description": "Micropayment of $0.000100 USDC for Benchmark run 87 validated"
    },
    {
      "timestamp": "2026-06-05T03:05:43.813Z",
      "type": "MICRO-PAYMENT",
      "channelId": "0xcb7b7c23c32c77123256cb6540cbd156c496d6865ce071768b66470225ea48af",
      "amount": "0.000100",
      "recipient": "0x3C44CdDdB6a900fa2b585dd299e03d12FA4293BC",
      "status": "SUCCESS",
      "description": "Micropayment of $0.000100 USDC for Benchmark run 86 validated"
    },
    {
      "timestamp": "2026-06-05T03:05:43.790Z",
      "type": "MICRO-PAYMENT",
      "channelId": "0xcb7b7c23c32c77123256cb6540cbd156c496d6865ce071768b66470225ea48af",
      "amount": "0.000100",
      "recipient": "0x3C44CdDdB6a900fa2b585dd299e03d12FA4293BC",
      "status": "SUCCESS",
      "description": "Micropayment of $0.000100 USDC for Benchmark run 85 validated"
    },
    {
      "timestamp": "2026-06-05T03:05:43.771Z",
      "type": "MICRO-PAYMENT",
      "channelId": "0xcb7b7c23c32c77123256cb6540cbd156c496d6865ce071768b66470225ea48af",
      "amount": "0.000100",
      "recipient": "0x3C44CdDdB6a900fa2b585dd299e03d12FA4293BC",
      "status": "SUCCESS",
      "description": "Micropayment of $0.000100 USDC for Benchmark run 84 validated"
    },
    {
      "timestamp": "2026-06-05T03:05:43.750Z",
      "type": "MICRO-PAYMENT",
      "channelId": "0xcb7b7c23c32c77123256cb6540cbd156c496d6865ce071768b66470225ea48af",
      "amount": "0.000100",
      "recipient": "0x3C44CdDdB6a900fa2b585dd299e03d12FA4293BC",
      "status": "SUCCESS",
      "description": "Micropayment of $0.000100 USDC for Benchmark run 83 validated"
    },
    {
      "timestamp": "2026-06-05T03:05:43.724Z",
      "type": "MICRO-PAYMENT",
      "channelId": "0xcb7b7c23c32c77123256cb6540cbd156c496d6865ce071768b66470225ea48af",
      "amount": "0.000100",
      "recipient": "0x3C44CdDdB6a900fa2b585dd299e03d12FA4293BC",
      "status": "SUCCESS",
      "description": "Micropayment of $0.000100 USDC for Benchmark run 82 validated"
    },
    {
      "timestamp": "2026-06-05T03:05:43.701Z",
      "type": "MICRO-PAYMENT",
      "channelId": "0xcb7b7c23c32c77123256cb6540cbd156c496d6865ce071768b66470225ea48af",
      "amount": "0.000100",
      "recipient": "0x3C44CdDdB6a900fa2b585dd299e03d12FA4293BC",
      "status": "SUCCESS",
      "description": "Micropayment of $0.000100 USDC for Benchmark run 81 validated"
    },
    {
      "timestamp": "2026-06-05T03:05:43.675Z",
      "type": "MICRO-PAYMENT",
      "channelId": "0xcb7b7c23c32c77123256cb6540cbd156c496d6865ce071768b66470225ea48af",
      "amount": "0.000100",
      "recipient": "0x3C44CdDdB6a900fa2b585dd299e03d12FA4293BC",
      "status": "SUCCESS",
      "description": "Micropayment of $0.000100 USDC for Benchmark run 80 validated"
    },
    {
      "timestamp": "2026-06-05T03:05:43.651Z",
      "type": "MICRO-PAYMENT",
      "channelId": "0xcb7b7c23c32c77123256cb6540cbd156c496d6865ce071768b66470225ea48af",
      "amount": "0.000100",
      "recipient": "0x3C44CdDdB6a900fa2b585dd299e03d12FA4293BC",
      "status": "SUCCESS",
      "description": "Micropayment of $0.000100 USDC for Benchmark run 79 validated"
    },
    {
      "timestamp": "2026-06-05T03:05:43.633Z",
      "type": "MICRO-PAYMENT",
      "channelId": "0xcb7b7c23c32c77123256cb6540cbd156c496d6865ce071768b66470225ea48af",
      "amount": "0.000100",
      "recipient": "0x3C44CdDdB6a900fa2b585dd299e03d12FA4293BC",
      "status": "SUCCESS",
      "description": "Micropayment of $0.000100 USDC for Benchmark run 78 validated"
    },
    {
      "timestamp": "2026-06-05T03:05:43.613Z",
      "type": "MICRO-PAYMENT",
      "channelId": "0xcb7b7c23c32c77123256cb6540cbd156c496d6865ce071768b66470225ea48af",
      "amount": "0.000100",
      "recipient": "0x3C44CdDdB6a900fa2b585dd299e03d12FA4293BC",
      "status": "SUCCESS",
      "description": "Micropayment of $0.000100 USDC for Benchmark run 77 validated"
    },
    {
      "timestamp": "2026-06-05T03:05:43.596Z",
      "type": "MICRO-PAYMENT",
      "channelId": "0xcb7b7c23c32c77123256cb6540cbd156c496d6865ce071768b66470225ea48af",
      "amount": "0.000100",
      "recipient": "0x3C44CdDdB6a900fa2b585dd299e03d12FA4293BC",
      "status": "SUCCESS",
      "description": "Micropayment of $0.000100 USDC for Benchmark run 76 validated"
    },
    {
      "timestamp": "2026-06-05T03:05:43.575Z",
      "type": "MICRO-PAYMENT",
      "channelId": "0xcb7b7c23c32c77123256cb6540cbd156c496d6865ce071768b66470225ea48af",
      "amount": "0.000100",
      "recipient": "0x3C44CdDdB6a900fa2b585dd299e03d12FA4293BC",
      "status": "SUCCESS",
      "description": "Micropayment of $0.000100 USDC for Benchmark run 75 validated"
    },
    {
      "timestamp": "2026-06-05T03:05:43.557Z",
      "type": "MICRO-PAYMENT",
      "channelId": "0xcb7b7c23c32c77123256cb6540cbd156c496d6865ce071768b66470225ea48af",
      "amount": "0.000100",
      "recipient": "0x3C44CdDdB6a900fa2b585dd299e03d12FA4293BC",
      "status": "SUCCESS",
      "description": "Micropayment of $0.000100 USDC for Benchmark run 74 validated"
    },
    {
      "timestamp": "2026-06-05T03:05:43.540Z",
      "type": "MICRO-PAYMENT",
      "channelId": "0xcb7b7c23c32c77123256cb6540cbd156c496d6865ce071768b66470225ea48af",
      "amount": "0.000100",
      "recipient": "0x3C44CdDdB6a900fa2b585dd299e03d12FA4293BC",
      "status": "SUCCESS",
      "description": "Micropayment of $0.000100 USDC for Benchmark run 73 validated"
    },
    {
      "timestamp": "2026-06-05T03:05:43.520Z",
      "type": "MICRO-PAYMENT",
      "channelId": "0xcb7b7c23c32c77123256cb6540cbd156c496d6865ce071768b66470225ea48af",
      "amount": "0.000100",
      "recipient": "0x3C44CdDdB6a900fa2b585dd299e03d12FA4293BC",
      "status": "SUCCESS",
      "description": "Micropayment of $0.000100 USDC for Benchmark run 72 validated"
    },
    {
      "timestamp": "2026-06-05T03:05:43.501Z",
      "type": "MICRO-PAYMENT",
      "channelId": "0xcb7b7c23c32c77123256cb6540cbd156c496d6865ce071768b66470225ea48af",
      "amount": "0.000100",
      "recipient": "0x3C44CdDdB6a900fa2b585dd299e03d12FA4293BC",
      "status": "SUCCESS",
      "description": "Micropayment of $0.000100 USDC for Benchmark run 71 validated"
    },
    {
      "timestamp": "2026-06-05T03:05:43.484Z",
      "type": "MICRO-PAYMENT",
      "channelId": "0xcb7b7c23c32c77123256cb6540cbd156c496d6865ce071768b66470225ea48af",
      "amount": "0.000100",
      "recipient": "0x3C44CdDdB6a900fa2b585dd299e03d12FA4293BC",
      "status": "SUCCESS",
      "description": "Micropayment of $0.000100 USDC for Benchmark run 70 validated"
    },
    {
      "timestamp": "2026-06-05T03:05:43.466Z",
      "type": "MICRO-PAYMENT",
      "channelId": "0xcb7b7c23c32c77123256cb6540cbd156c496d6865ce071768b66470225ea48af",
      "amount": "0.000100",
      "recipient": "0x3C44CdDdB6a900fa2b585dd299e03d12FA4293BC",
      "status": "SUCCESS",
      "description": "Micropayment of $0.000100 USDC for Benchmark run 69 validated"
    },
    {
      "timestamp": "2026-06-05T03:05:43.448Z",
      "type": "MICRO-PAYMENT",
      "channelId": "0xcb7b7c23c32c77123256cb6540cbd156c496d6865ce071768b66470225ea48af",
      "amount": "0.000100",
      "recipient": "0x3C44CdDdB6a900fa2b585dd299e03d12FA4293BC",
      "status": "SUCCESS",
      "description": "Micropayment of $0.000100 USDC for Benchmark run 68 validated"
    },
    {
      "timestamp": "2026-06-05T03:05:43.423Z",
      "type": "MICRO-PAYMENT",
      "channelId": "0xcb7b7c23c32c77123256cb6540cbd156c496d6865ce071768b66470225ea48af",
      "amount": "0.000100",
      "recipient": "0x3C44CdDdB6a900fa2b585dd299e03d12FA4293BC",
      "status": "SUCCESS",
      "description": "Micropayment of $0.000100 USDC for Benchmark run 67 validated"
    },
    {
      "timestamp": "2026-06-05T03:05:43.399Z",
      "type": "MICRO-PAYMENT",
      "channelId": "0xcb7b7c23c32c77123256cb6540cbd156c496d6865ce071768b66470225ea48af",
      "amount": "0.000100",
      "recipient": "0x3C44CdDdB6a900fa2b585dd299e03d12FA4293BC",
      "status": "SUCCESS",
      "description": "Micropayment of $0.000100 USDC for Benchmark run 66 validated"
    },
    {
      "timestamp": "2026-06-05T03:05:43.382Z",
      "type": "MICRO-PAYMENT",
      "channelId": "0xcb7b7c23c32c77123256cb6540cbd156c496d6865ce071768b66470225ea48af",
      "amount": "0.000100",
      "recipient": "0x3C44CdDdB6a900fa2b585dd299e03d12FA4293BC",
      "status": "SUCCESS",
      "description": "Micropayment of $0.000100 USDC for Benchmark run 65 validated"
    },
    {
      "timestamp": "2026-06-05T03:05:43.364Z",
      "type": "MICRO-PAYMENT",
      "channelId": "0xcb7b7c23c32c77123256cb6540cbd156c496d6865ce071768b66470225ea48af",
      "amount": "0.000100",
      "recipient": "0x3C44CdDdB6a900fa2b585dd299e03d12FA4293BC",
      "status": "SUCCESS",
      "description": "Micropayment of $0.000100 USDC for Benchmark run 64 validated"
    },
    {
      "timestamp": "2026-06-05T03:05:43.346Z",
      "type": "MICRO-PAYMENT",
      "channelId": "0xcb7b7c23c32c77123256cb6540cbd156c496d6865ce071768b66470225ea48af",
      "amount": "0.000100",
      "recipient": "0x3C44CdDdB6a900fa2b585dd299e03d12FA4293BC",
      "status": "SUCCESS",
      "description": "Micropayment of $0.000100 USDC for Benchmark run 63 validated"
    },
    {
      "timestamp": "2026-06-05T03:05:43.326Z",
      "type": "MICRO-PAYMENT",
      "channelId": "0xcb7b7c23c32c77123256cb6540cbd156c496d6865ce071768b66470225ea48af",
      "amount": "0.000100",
      "recipient": "0x3C44CdDdB6a900fa2b585dd299e03d12FA4293BC",
      "status": "SUCCESS",
      "description": "Micropayment of $0.000100 USDC for Benchmark run 62 validated"
    },
    {
      "timestamp": "2026-06-05T03:05:43.306Z",
      "type": "MICRO-PAYMENT",
      "channelId": "0xcb7b7c23c32c77123256cb6540cbd156c496d6865ce071768b66470225ea48af",
      "amount": "0.000100",
      "recipient": "0x3C44CdDdB6a900fa2b585dd299e03d12FA4293BC",
      "status": "SUCCESS",
      "description": "Micropayment of $0.000100 USDC for Benchmark run 61 validated"
    },
    {
      "timestamp": "2026-06-05T03:05:43.287Z",
      "type": "MICRO-PAYMENT",
      "channelId": "0xcb7b7c23c32c77123256cb6540cbd156c496d6865ce071768b66470225ea48af",
      "amount": "0.000100",
      "recipient": "0x3C44CdDdB6a900fa2b585dd299e03d12FA4293BC",
      "status": "SUCCESS",
      "description": "Micropayment of $0.000100 USDC for Benchmark run 60 validated"
    },
    {
      "timestamp": "2026-06-05T03:05:43.268Z",
      "type": "MICRO-PAYMENT",
      "channelId": "0xcb7b7c23c32c77123256cb6540cbd156c496d6865ce071768b66470225ea48af",
      "amount": "0.000100",
      "recipient": "0x3C44CdDdB6a900fa2b585dd299e03d12FA4293BC",
      "status": "SUCCESS",
      "description": "Micropayment of $0.000100 USDC for Benchmark run 59 validated"
    },
    {
      "timestamp": "2026-06-05T03:05:43.243Z",
      "type": "MICRO-PAYMENT",
      "channelId": "0xcb7b7c23c32c77123256cb6540cbd156c496d6865ce071768b66470225ea48af",
      "amount": "0.000100",
      "recipient": "0x3C44CdDdB6a900fa2b585dd299e03d12FA4293BC",
      "status": "SUCCESS",
      "description": "Micropayment of $0.000100 USDC for Benchmark run 58 validated"
    },
    {
      "timestamp": "2026-06-05T03:05:43.223Z",
      "type": "MICRO-PAYMENT",
      "channelId": "0xcb7b7c23c32c77123256cb6540cbd156c496d6865ce071768b66470225ea48af",
      "amount": "0.000100",
      "recipient": "0x3C44CdDdB6a900fa2b585dd299e03d12FA4293BC",
      "status": "SUCCESS",
      "description": "Micropayment of $0.000100 USDC for Benchmark run 57 validated"
    },
    {
      "timestamp": "2026-06-05T03:05:43.202Z",
      "type": "MICRO-PAYMENT",
      "channelId": "0xcb7b7c23c32c77123256cb6540cbd156c496d6865ce071768b66470225ea48af",
      "amount": "0.000100",
      "recipient": "0x3C44CdDdB6a900fa2b585dd299e03d12FA4293BC",
      "status": "SUCCESS",
      "description": "Micropayment of $0.000100 USDC for Benchmark run 56 validated"
    },
    {
      "timestamp": "2026-06-05T03:05:43.181Z",
      "type": "MICRO-PAYMENT",
      "channelId": "0xcb7b7c23c32c77123256cb6540cbd156c496d6865ce071768b66470225ea48af",
      "amount": "0.000100",
      "recipient": "0x3C44CdDdB6a900fa2b585dd299e03d12FA4293BC",
      "status": "SUCCESS",
      "description": "Micropayment of $0.000100 USDC for Benchmark run 55 validated"
    },
    {
      "timestamp": "2026-06-05T03:05:43.162Z",
      "type": "MICRO-PAYMENT",
      "channelId": "0xcb7b7c23c32c77123256cb6540cbd156c496d6865ce071768b66470225ea48af",
      "amount": "0.000100",
      "recipient": "0x3C44CdDdB6a900fa2b585dd299e03d12FA4293BC",
      "status": "SUCCESS",
      "description": "Micropayment of $0.000100 USDC for Benchmark run 54 validated"
    },
    {
      "timestamp": "2026-06-05T03:05:43.144Z",
      "type": "MICRO-PAYMENT",
      "channelId": "0xcb7b7c23c32c77123256cb6540cbd156c496d6865ce071768b66470225ea48af",
      "amount": "0.000100",
      "recipient": "0x3C44CdDdB6a900fa2b585dd299e03d12FA4293BC",
      "status": "SUCCESS",
      "description": "Micropayment of $0.000100 USDC for Benchmark run 53 validated"
    },
    {
      "timestamp": "2026-06-05T03:05:43.126Z",
      "type": "MICRO-PAYMENT",
      "channelId": "0xcb7b7c23c32c77123256cb6540cbd156c496d6865ce071768b66470225ea48af",
      "amount": "0.000100",
      "recipient": "0x3C44CdDdB6a900fa2b585dd299e03d12FA4293BC",
      "status": "SUCCESS",
      "description": "Micropayment of $0.000100 USDC for Benchmark run 52 validated"
    },
    {
      "timestamp": "2026-06-05T03:05:43.106Z",
      "type": "MICRO-PAYMENT",
      "channelId": "0xcb7b7c23c32c77123256cb6540cbd156c496d6865ce071768b66470225ea48af",
      "amount": "0.000100",
      "recipient": "0x3C44CdDdB6a900fa2b585dd299e03d12FA4293BC",
      "status": "SUCCESS",
      "description": "Micropayment of $0.000100 USDC for Benchmark run 51 validated"
    },
    {
      "timestamp": "2026-06-05T03:05:43.086Z",
      "type": "MICRO-PAYMENT",
      "channelId": "0xcb7b7c23c32c77123256cb6540cbd156c496d6865ce071768b66470225ea48af",
      "amount": "0.000100",
      "recipient": "0x3C44CdDdB6a900fa2b585dd299e03d12FA4293BC",
      "status": "SUCCESS",
      "description": "Micropayment of $0.000100 USDC for Benchmark run 50 validated"
    },
    {
      "timestamp": "2026-06-05T03:05:43.064Z",
      "type": "MICRO-PAYMENT",
      "channelId": "0xcb7b7c23c32c77123256cb6540cbd156c496d6865ce071768b66470225ea48af",
      "amount": "0.000100",
      "recipient": "0x3C44CdDdB6a900fa2b585dd299e03d12FA4293BC",
      "status": "SUCCESS",
      "description": "Micropayment of $0.000100 USDC for Benchmark run 49 validated"
    },
    {
      "timestamp": "2026-06-05T03:05:43.044Z",
      "type": "MICRO-PAYMENT",
      "channelId": "0xcb7b7c23c32c77123256cb6540cbd156c496d6865ce071768b66470225ea48af",
      "amount": "0.000100",
      "recipient": "0x3C44CdDdB6a900fa2b585dd299e03d12FA4293BC",
      "status": "SUCCESS",
      "description": "Micropayment of $0.000100 USDC for Benchmark run 48 validated"
    },
    {
      "timestamp": "2026-06-05T03:05:43.023Z",
      "type": "MICRO-PAYMENT",
      "channelId": "0xcb7b7c23c32c77123256cb6540cbd156c496d6865ce071768b66470225ea48af",
      "amount": "0.000100",
      "recipient": "0x3C44CdDdB6a900fa2b585dd299e03d12FA4293BC",
      "status": "SUCCESS",
      "description": "Micropayment of $0.000100 USDC for Benchmark run 47 validated"
    },
    {
      "timestamp": "2026-06-05T03:05:43.005Z",
      "type": "MICRO-PAYMENT",
      "channelId": "0xcb7b7c23c32c77123256cb6540cbd156c496d6865ce071768b66470225ea48af",
      "amount": "0.000100",
      "recipient": "0x3C44CdDdB6a900fa2b585dd299e03d12FA4293BC",
      "status": "SUCCESS",
      "description": "Micropayment of $0.000100 USDC for Benchmark run 46 validated"
    },
    {
      "timestamp": "2026-06-05T03:05:42.984Z",
      "type": "MICRO-PAYMENT",
      "channelId": "0xcb7b7c23c32c77123256cb6540cbd156c496d6865ce071768b66470225ea48af",
      "amount": "0.000100",
      "recipient": "0x3C44CdDdB6a900fa2b585dd299e03d12FA4293BC",
      "status": "SUCCESS",
      "description": "Micropayment of $0.000100 USDC for Benchmark run 45 validated"
    },
    {
      "timestamp": "2026-06-05T03:05:42.959Z",
      "type": "MICRO-PAYMENT",
      "channelId": "0xcb7b7c23c32c77123256cb6540cbd156c496d6865ce071768b66470225ea48af",
      "amount": "0.000100",
      "recipient": "0x3C44CdDdB6a900fa2b585dd299e03d12FA4293BC",
      "status": "SUCCESS",
      "description": "Micropayment of $0.000100 USDC for Benchmark run 44 validated"
    },
    {
      "timestamp": "2026-06-05T03:05:42.935Z",
      "type": "MICRO-PAYMENT",
      "channelId": "0xcb7b7c23c32c77123256cb6540cbd156c496d6865ce071768b66470225ea48af",
      "amount": "0.000100",
      "recipient": "0x3C44CdDdB6a900fa2b585dd299e03d12FA4293BC",
      "status": "SUCCESS",
      "description": "Micropayment of $0.000100 USDC for Benchmark run 43 validated"
    },
    {
      "timestamp": "2026-06-05T03:05:42.910Z",
      "type": "MICRO-PAYMENT",
      "channelId": "0xcb7b7c23c32c77123256cb6540cbd156c496d6865ce071768b66470225ea48af",
      "amount": "0.000100",
      "recipient": "0x3C44CdDdB6a900fa2b585dd299e03d12FA4293BC",
      "status": "SUCCESS",
      "description": "Micropayment of $0.000100 USDC for Benchmark run 42 validated"
    },
    {
      "timestamp": "2026-06-05T03:05:42.882Z",
      "type": "MICRO-PAYMENT",
      "channelId": "0xcb7b7c23c32c77123256cb6540cbd156c496d6865ce071768b66470225ea48af",
      "amount": "0.000100",
      "recipient": "0x3C44CdDdB6a900fa2b585dd299e03d12FA4293BC",
      "status": "SUCCESS",
      "description": "Micropayment of $0.000100 USDC for Benchmark run 41 validated"
    },
    {
      "timestamp": "2026-06-05T03:05:42.856Z",
      "type": "MICRO-PAYMENT",
      "channelId": "0xcb7b7c23c32c77123256cb6540cbd156c496d6865ce071768b66470225ea48af",
      "amount": "0.000100",
      "recipient": "0x3C44CdDdB6a900fa2b585dd299e03d12FA4293BC",
      "status": "SUCCESS",
      "description": "Micropayment of $0.000100 USDC for Benchmark run 40 validated"
    },
    {
      "timestamp": "2026-06-05T03:05:42.827Z",
      "type": "MICRO-PAYMENT",
      "channelId": "0xcb7b7c23c32c77123256cb6540cbd156c496d6865ce071768b66470225ea48af",
      "amount": "0.000100",
      "recipient": "0x3C44CdDdB6a900fa2b585dd299e03d12FA4293BC",
      "status": "SUCCESS",
      "description": "Micropayment of $0.000100 USDC for Benchmark run 39 validated"
    },
    {
      "timestamp": "2026-06-05T03:05:42.804Z",
      "type": "MICRO-PAYMENT",
      "channelId": "0xcb7b7c23c32c77123256cb6540cbd156c496d6865ce071768b66470225ea48af",
      "amount": "0.000100",
      "recipient": "0x3C44CdDdB6a900fa2b585dd299e03d12FA4293BC",
      "status": "SUCCESS",
      "description": "Micropayment of $0.000100 USDC for Benchmark run 38 validated"
    },
    {
      "timestamp": "2026-06-05T03:05:42.783Z",
      "type": "MICRO-PAYMENT",
      "channelId": "0xcb7b7c23c32c77123256cb6540cbd156c496d6865ce071768b66470225ea48af",
      "amount": "0.000100",
      "recipient": "0x3C44CdDdB6a900fa2b585dd299e03d12FA4293BC",
      "status": "SUCCESS",
      "description": "Micropayment of $0.000100 USDC for Benchmark run 37 validated"
    },
    {
      "timestamp": "2026-06-05T03:05:42.755Z",
      "type": "MICRO-PAYMENT",
      "channelId": "0xcb7b7c23c32c77123256cb6540cbd156c496d6865ce071768b66470225ea48af",
      "amount": "0.000100",
      "recipient": "0x3C44CdDdB6a900fa2b585dd299e03d12FA4293BC",
      "status": "SUCCESS",
      "description": "Micropayment of $0.000100 USDC for Benchmark run 36 validated"
    },
    {
      "timestamp": "2026-06-05T03:05:42.734Z",
      "type": "MICRO-PAYMENT",
      "channelId": "0xcb7b7c23c32c77123256cb6540cbd156c496d6865ce071768b66470225ea48af",
      "amount": "0.000100",
      "recipient": "0x3C44CdDdB6a900fa2b585dd299e03d12FA4293BC",
      "status": "SUCCESS",
      "description": "Micropayment of $0.000100 USDC for Benchmark run 35 validated"
    },
    {
      "timestamp": "2026-06-05T03:05:42.710Z",
      "type": "MICRO-PAYMENT",
      "channelId": "0xcb7b7c23c32c77123256cb6540cbd156c496d6865ce071768b66470225ea48af",
      "amount": "0.000100",
      "recipient": "0x3C44CdDdB6a900fa2b585dd299e03d12FA4293BC",
      "status": "SUCCESS",
      "description": "Micropayment of $0.000100 USDC for Benchmark run 34 validated"
    },
    {
      "timestamp": "2026-06-05T03:05:42.681Z",
      "type": "MICRO-PAYMENT",
      "channelId": "0xcb7b7c23c32c77123256cb6540cbd156c496d6865ce071768b66470225ea48af",
      "amount": "0.000100",
      "recipient": "0x3C44CdDdB6a900fa2b585dd299e03d12FA4293BC",
      "status": "SUCCESS",
      "description": "Micropayment of $0.000100 USDC for Benchmark run 33 validated"
    },
    {
      "timestamp": "2026-06-05T03:05:42.620Z",
      "type": "MICRO-PAYMENT",
      "channelId": "0xcb7b7c23c32c77123256cb6540cbd156c496d6865ce071768b66470225ea48af",
      "amount": "0.000100",
      "recipient": "0x3C44CdDdB6a900fa2b585dd299e03d12FA4293BC",
      "status": "SUCCESS",
      "description": "Micropayment of $0.000100 USDC for Benchmark run 32 validated"
    },
    {
      "timestamp": "2026-06-05T03:05:42.574Z",
      "type": "MICRO-PAYMENT",
      "channelId": "0xcb7b7c23c32c77123256cb6540cbd156c496d6865ce071768b66470225ea48af",
      "amount": "0.000100",
      "recipient": "0x3C44CdDdB6a900fa2b585dd299e03d12FA4293BC",
      "status": "SUCCESS",
      "description": "Micropayment of $0.000100 USDC for Benchmark run 31 validated"
    },
    {
      "timestamp": "2026-06-05T03:05:42.541Z",
      "type": "MICRO-PAYMENT",
      "channelId": "0xcb7b7c23c32c77123256cb6540cbd156c496d6865ce071768b66470225ea48af",
      "amount": "0.000100",
      "recipient": "0x3C44CdDdB6a900fa2b585dd299e03d12FA4293BC",
      "status": "SUCCESS",
      "description": "Micropayment of $0.000100 USDC for Benchmark run 30 validated"
    },
    {
      "timestamp": "2026-06-05T03:05:42.497Z",
      "type": "MICRO-PAYMENT",
      "channelId": "0xcb7b7c23c32c77123256cb6540cbd156c496d6865ce071768b66470225ea48af",
      "amount": "0.000100",
      "recipient": "0x3C44CdDdB6a900fa2b585dd299e03d12FA4293BC",
      "status": "SUCCESS",
      "description": "Micropayment of $0.000100 USDC for Benchmark run 29 validated"
    },
    {
      "timestamp": "2026-06-05T03:05:42.468Z",
      "type": "MICRO-PAYMENT",
      "channelId": "0xcb7b7c23c32c77123256cb6540cbd156c496d6865ce071768b66470225ea48af",
      "amount": "0.000100",
      "recipient": "0x3C44CdDdB6a900fa2b585dd299e03d12FA4293BC",
      "status": "SUCCESS",
      "description": "Micropayment of $0.000100 USDC for Benchmark run 28 validated"
    },
    {
      "timestamp": "2026-06-05T03:05:42.440Z",
      "type": "MICRO-PAYMENT",
      "channelId": "0xcb7b7c23c32c77123256cb6540cbd156c496d6865ce071768b66470225ea48af",
      "amount": "0.000100",
      "recipient": "0x3C44CdDdB6a900fa2b585dd299e03d12FA4293BC",
      "status": "SUCCESS",
      "description": "Micropayment of $0.000100 USDC for Benchmark run 27 validated"
    },
    {
      "timestamp": "2026-06-05T03:05:42.416Z",
      "type": "MICRO-PAYMENT",
      "channelId": "0xcb7b7c23c32c77123256cb6540cbd156c496d6865ce071768b66470225ea48af",
      "amount": "0.000100",
      "recipient": "0x3C44CdDdB6a900fa2b585dd299e03d12FA4293BC",
      "status": "SUCCESS",
      "description": "Micropayment of $0.000100 USDC for Benchmark run 26 validated"
    },
    {
      "timestamp": "2026-06-05T03:05:42.390Z",
      "type": "MICRO-PAYMENT",
      "channelId": "0xcb7b7c23c32c77123256cb6540cbd156c496d6865ce071768b66470225ea48af",
      "amount": "0.000100",
      "recipient": "0x3C44CdDdB6a900fa2b585dd299e03d12FA4293BC",
      "status": "SUCCESS",
      "description": "Micropayment of $0.000100 USDC for Benchmark run 25 validated"
    },
    {
      "timestamp": "2026-06-05T03:05:42.364Z",
      "type": "MICRO-PAYMENT",
      "channelId": "0xcb7b7c23c32c77123256cb6540cbd156c496d6865ce071768b66470225ea48af",
      "amount": "0.000100",
      "recipient": "0x3C44CdDdB6a900fa2b585dd299e03d12FA4293BC",
      "status": "SUCCESS",
      "description": "Micropayment of $0.000100 USDC for Benchmark run 24 validated"
    },
    {
      "timestamp": "2026-06-05T03:05:42.342Z",
      "type": "MICRO-PAYMENT",
      "channelId": "0xcb7b7c23c32c77123256cb6540cbd156c496d6865ce071768b66470225ea48af",
      "amount": "0.000100",
      "recipient": "0x3C44CdDdB6a900fa2b585dd299e03d12FA4293BC",
      "status": "SUCCESS",
      "description": "Micropayment of $0.000100 USDC for Benchmark run 23 validated"
    },
    {
      "timestamp": "2026-06-05T03:05:42.303Z",
      "type": "MICRO-PAYMENT",
      "channelId": "0xcb7b7c23c32c77123256cb6540cbd156c496d6865ce071768b66470225ea48af",
      "amount": "0.000100",
      "recipient": "0x3C44CdDdB6a900fa2b585dd299e03d12FA4293BC",
      "status": "SUCCESS",
      "description": "Micropayment of $0.000100 USDC for Benchmark run 22 validated"
    },
    {
      "timestamp": "2026-06-05T03:05:42.267Z",
      "type": "MICRO-PAYMENT",
      "channelId": "0xcb7b7c23c32c77123256cb6540cbd156c496d6865ce071768b66470225ea48af",
      "amount": "0.000100",
      "recipient": "0x3C44CdDdB6a900fa2b585dd299e03d12FA4293BC",
      "status": "SUCCESS",
      "description": "Micropayment of $0.000100 USDC for Benchmark run 21 validated"
    },
    {
      "timestamp": "2026-06-05T03:05:42.232Z",
      "type": "MICRO-PAYMENT",
      "channelId": "0xcb7b7c23c32c77123256cb6540cbd156c496d6865ce071768b66470225ea48af",
      "amount": "0.000100",
      "recipient": "0x3C44CdDdB6a900fa2b585dd299e03d12FA4293BC",
      "status": "SUCCESS",
      "description": "Micropayment of $0.000100 USDC for Benchmark run 20 validated"
    },
    {
      "timestamp": "2026-06-05T03:05:42.207Z",
      "type": "MICRO-PAYMENT",
      "channelId": "0xcb7b7c23c32c77123256cb6540cbd156c496d6865ce071768b66470225ea48af",
      "amount": "0.000100",
      "recipient": "0x3C44CdDdB6a900fa2b585dd299e03d12FA4293BC",
      "status": "SUCCESS",
      "description": "Micropayment of $0.000100 USDC for Benchmark run 19 validated"
    },
    {
      "timestamp": "2026-06-05T03:05:42.180Z",
      "type": "MICRO-PAYMENT",
      "channelId": "0xcb7b7c23c32c77123256cb6540cbd156c496d6865ce071768b66470225ea48af",
      "amount": "0.000100",
      "recipient": "0x3C44CdDdB6a900fa2b585dd299e03d12FA4293BC",
      "status": "SUCCESS",
      "description": "Micropayment of $0.000100 USDC for Benchmark run 18 validated"
    },
    {
      "timestamp": "2026-06-05T03:05:42.154Z",
      "type": "MICRO-PAYMENT",
      "channelId": "0xcb7b7c23c32c77123256cb6540cbd156c496d6865ce071768b66470225ea48af",
      "amount": "0.000100",
      "recipient": "0x3C44CdDdB6a900fa2b585dd299e03d12FA4293BC",
      "status": "SUCCESS",
      "description": "Micropayment of $0.000100 USDC for Benchmark run 17 validated"
    },
    {
      "timestamp": "2026-06-05T03:05:42.127Z",
      "type": "MICRO-PAYMENT",
      "channelId": "0xcb7b7c23c32c77123256cb6540cbd156c496d6865ce071768b66470225ea48af",
      "amount": "0.000100",
      "recipient": "0x3C44CdDdB6a900fa2b585dd299e03d12FA4293BC",
      "status": "SUCCESS",
      "description": "Micropayment of $0.000100 USDC for Benchmark run 16 validated"
    },
    {
      "timestamp": "2026-06-05T03:05:42.097Z",
      "type": "MICRO-PAYMENT",
      "channelId": "0xcb7b7c23c32c77123256cb6540cbd156c496d6865ce071768b66470225ea48af",
      "amount": "0.000100",
      "recipient": "0x3C44CdDdB6a900fa2b585dd299e03d12FA4293BC",
      "status": "SUCCESS",
      "description": "Micropayment of $0.000100 USDC for Benchmark run 15 validated"
    },
    {
      "timestamp": "2026-06-05T03:05:42.064Z",
      "type": "MICRO-PAYMENT",
      "channelId": "0xcb7b7c23c32c77123256cb6540cbd156c496d6865ce071768b66470225ea48af",
      "amount": "0.000100",
      "recipient": "0x3C44CdDdB6a900fa2b585dd299e03d12FA4293BC",
      "status": "SUCCESS",
      "description": "Micropayment of $0.000100 USDC for Benchmark run 14 validated"
    },
    {
      "timestamp": "2026-06-05T03:05:42.030Z",
      "type": "MICRO-PAYMENT",
      "channelId": "0xcb7b7c23c32c77123256cb6540cbd156c496d6865ce071768b66470225ea48af",
      "amount": "0.000100",
      "recipient": "0x3C44CdDdB6a900fa2b585dd299e03d12FA4293BC",
      "status": "SUCCESS",
      "description": "Micropayment of $0.000100 USDC for Benchmark run 13 validated"
    },
    {
      "timestamp": "2026-06-05T03:05:42.003Z",
      "type": "MICRO-PAYMENT",
      "channelId": "0xcb7b7c23c32c77123256cb6540cbd156c496d6865ce071768b66470225ea48af",
      "amount": "0.000100",
      "recipient": "0x3C44CdDdB6a900fa2b585dd299e03d12FA4293BC",
      "status": "SUCCESS",
      "description": "Micropayment of $0.000100 USDC for Benchmark run 12 validated"
    },
    {
      "timestamp": "2026-06-05T03:05:41.978Z",
      "type": "MICRO-PAYMENT",
      "channelId": "0xcb7b7c23c32c77123256cb6540cbd156c496d6865ce071768b66470225ea48af",
      "amount": "0.000100",
      "recipient": "0x3C44CdDdB6a900fa2b585dd299e03d12FA4293BC",
      "status": "SUCCESS",
      "description": "Micropayment of $0.000100 USDC for Benchmark run 11 validated"
    },
    {
      "timestamp": "2026-06-05T03:05:41.952Z",
      "type": "MICRO-PAYMENT",
      "channelId": "0xcb7b7c23c32c77123256cb6540cbd156c496d6865ce071768b66470225ea48af",
      "amount": "0.000100",
      "recipient": "0x3C44CdDdB6a900fa2b585dd299e03d12FA4293BC",
      "status": "SUCCESS",
      "description": "Micropayment of $0.000100 USDC for Benchmark run 10 validated"
    },
    {
      "timestamp": "2026-06-05T03:05:41.927Z",
      "type": "MICRO-PAYMENT",
      "channelId": "0xcb7b7c23c32c77123256cb6540cbd156c496d6865ce071768b66470225ea48af",
      "amount": "0.000100",
      "recipient": "0x3C44CdDdB6a900fa2b585dd299e03d12FA4293BC",
      "status": "SUCCESS",
      "description": "Micropayment of $0.000100 USDC for Benchmark run 9 validated"
    },
    {
      "timestamp": "2026-06-05T03:05:41.904Z",
      "type": "MICRO-PAYMENT",
      "channelId": "0xcb7b7c23c32c77123256cb6540cbd156c496d6865ce071768b66470225ea48af",
      "amount": "0.000100",
      "recipient": "0x3C44CdDdB6a900fa2b585dd299e03d12FA4293BC",
      "status": "SUCCESS",
      "description": "Micropayment of $0.000100 USDC for Benchmark run 8 validated"
    },
    {
      "timestamp": "2026-06-05T03:05:41.880Z",
      "type": "MICRO-PAYMENT",
      "channelId": "0xcb7b7c23c32c77123256cb6540cbd156c496d6865ce071768b66470225ea48af",
      "amount": "0.000100",
      "recipient": "0x3C44CdDdB6a900fa2b585dd299e03d12FA4293BC",
      "status": "SUCCESS",
      "description": "Micropayment of $0.000100 USDC for Benchmark run 7 validated"
    },
    {
      "timestamp": "2026-06-05T03:05:41.854Z",
      "type": "MICRO-PAYMENT",
      "channelId": "0xcb7b7c23c32c77123256cb6540cbd156c496d6865ce071768b66470225ea48af",
      "amount": "0.000100",
      "recipient": "0x3C44CdDdB6a900fa2b585dd299e03d12FA4293BC",
      "status": "SUCCESS",
      "description": "Micropayment of $0.000100 USDC for Benchmark run 6 validated"
    },
    {
      "timestamp": "2026-06-05T03:05:41.830Z",
      "type": "MICRO-PAYMENT",
      "channelId": "0xcb7b7c23c32c77123256cb6540cbd156c496d6865ce071768b66470225ea48af",
      "amount": "0.000100",
      "recipient": "0x3C44CdDdB6a900fa2b585dd299e03d12FA4293BC",
      "status": "SUCCESS",
      "description": "Micropayment of $0.000100 USDC for Benchmark run 5 validated"
    },
    {
      "timestamp": "2026-06-05T03:05:41.794Z",
      "type": "MICRO-PAYMENT",
      "channelId": "0xcb7b7c23c32c77123256cb6540cbd156c496d6865ce071768b66470225ea48af",
      "amount": "0.000100",
      "recipient": "0x3C44CdDdB6a900fa2b585dd299e03d12FA4293BC",
      "status": "SUCCESS",
      "description": "Micropayment of $0.000100 USDC for Benchmark run 4 validated"
    },
    {
      "timestamp": "2026-06-05T03:05:41.765Z",
      "type": "MICRO-PAYMENT",
      "channelId": "0xcb7b7c23c32c77123256cb6540cbd156c496d6865ce071768b66470225ea48af",
      "amount": "0.000100",
      "recipient": "0x3C44CdDdB6a900fa2b585dd299e03d12FA4293BC",
      "status": "SUCCESS",
      "description": "Micropayment of $0.000100 USDC for Benchmark run 3 validated"
    },
    {
      "timestamp": "2026-06-05T03:05:41.724Z",
      "type": "MICRO-PAYMENT",
      "channelId": "0xcb7b7c23c32c77123256cb6540cbd156c496d6865ce071768b66470225ea48af",
      "amount": "0.000100",
      "recipient": "0x3C44CdDdB6a900fa2b585dd299e03d12FA4293BC",
      "status": "SUCCESS",
      "description": "Micropayment of $0.000100 USDC for Benchmark run 2 validated"
    },
    {
      "timestamp": "2026-06-05T03:05:41.681Z",
      "type": "MICRO-PAYMENT",
      "channelId": "0xcb7b7c23c32c77123256cb6540cbd156c496d6865ce071768b66470225ea48af",
      "amount": "0.000100",
      "recipient": "0x3C44CdDdB6a900fa2b585dd299e03d12FA4293BC",
      "status": "SUCCESS",
      "description": "Micropayment of $0.000100 USDC for Benchmark run 1 validated"
    },
    {
      "timestamp": "2026-06-05T03:05:41.632Z",
      "type": "MICRO-PAYMENT",
      "channelId": "0xcb7b7c23c32c77123256cb6540cbd156c496d6865ce071768b66470225ea48af",
      "amount": "0.000100",
      "recipient": "0x3C44CdDdB6a900fa2b585dd299e03d12FA4293BC",
      "status": "SUCCESS",
      "description": "Micropayment of $0.000100 USDC for Benchmark run 0 validated"
    },
    {
      "timestamp": "2026-06-05T03:05:41.590Z",
      "type": "DEPOSIT",
      "channelId": "0xcb7b7c23c32c77123256cb6540cbd156c496d6865ce071768b66470225ea48af",
      "amount": "10.000000",
      "recipient": "0x3C44CdDdB6a900fa2b585dd299e03d12FA4293BC",
      "status": "SUCCESS",
      "description": "Opened payment channel with initial deposit of $10.00 USDC"
    }
  ]
}